{
  "$schema": "https://schema.tauri.app/config/2",
  "productName": "Pulsecrate",
  "version": "0.1.0",
  "identifier": "studio.pulsecrate.app",
  "build": {
    "beforeDevCommand": "npm run dev",
    "devUrl": "http://127.0.0.1:5173",
    "beforeBuildCommand": "npm run build",
    "frontendDist": "../dist"
  },
  "app": {
    "windows": [
      {
        "title": "Pulsecrate",
        "width": 1440,
        "height": 940,
        "minWidth": 1024,
        "minHeight": 720
      }
    ],
    "security": {
      "csp": null
    }
  },
  "bundle": {
    "active": true,
    "targets": "all",
    "icon": [
      "../application.ico"
    ]
  }
}
